output_decorator/__init__.py
output_decorator/decorators.py
outputdecorator-0.1.0.dist-info/licenses/LICENSE
outputdecorator-0.1.0.dist-info/METADATA
outputdecorator-0.1.0.dist-info/WHEEL
outputdecorator-0.1.0.dist-info/top_level.txt
outputdecorator-0.1.0.dist-info/RECORD
