Metadata-Version: 2.4
Name: outputdecorator
Version: 0.1.0
Summary: Library for decorating strings in CLI apps.
Author-email: Alexander Suvorov <aixandrolab@gmail.com>
License-Expression: BSD-3-Clause
Project-URL: Homepage, https://github.com/aixandrolab/outputdecorator
Classifier: Programming Language :: Python :: 3
Classifier: Programming Language :: Python :: 3.7
Classifier: Programming Language :: Python :: 3.8
Classifier: Programming Language :: Python :: 3.9
Classifier: Programming Language :: Python :: 3.10
Classifier: Programming Language :: Python :: 3.11
Classifier: Programming Language :: Python :: 3.12
Requires-Python: >=3.6
License-File: LICENSE
Dynamic: license-file
